{
  "A.J. Lawson": 0.576,
  "AJ Green": 0.519,
  "AJ Johnson": 0.623,
  "Aaron Gordon": 0.527,
  "Aaron Holiday": 0.612,
  "Aaron Nesmith": 0.512,
  "Aaron Wiggins": 0.6,
  "Ace Bailey": 0.5,
  "Adam Flagler": 0.792,
  "Adem Bona": 0.535,
  "Adou Thiero": 0.909,
  "Ajay Mitchell": 0.443,
  "Al Horford": 0.538,
  "Alec Burks": 0.513,
  "Alex Caruso": 0.531,
  "Alex Ducas": 0.909,
  "Alex Len": 0.765,
  "Alex Sarr": 0.486,
  "Alperen Sengun": 0.556,
  "Amari Williams": 0.9,
  "Amen Thompson": 0.444,
  "Amir Coffey": 0.648,
  "Andre Drummond": 0.598,
  "Andre Jackson Jr.": 0.663,
  "Andrew Nembhard": 0.545,
  "Andrew Wiggins": 0.504,
  "Anfernee Simons": 0.504,
  "Anthony Black": 0.469,
  "Anthony Davis": 0.574,
  "Anthony Edwards": 0.508,
  "Anthony Gill": 0.588,
  "Antonio Reeves": 0.636,
  "Ariel Hukporti": 0.769,
  "Asa Newell": 0.533,
  "Ausar Thompson": 0.569,
  "Austin Reaves": 0.504,
  "Ayo Dosunmu": 0.43,
  "Bam Adebayo": 0.449,
  "Baylor Scheierman": 0.609,
  "Ben Saraf": 0.448,
  "Ben Sheppard": 0.624,
  "Ben Simmons": 0.683,
  "Bennedict Mathurin": 0.536,
  "Bilal Coulibaly": 0.52,
  "Bismack Biyombo": 0.775,
  "Blake Wesley": 0.573,
  "Bobby Portis": 0.453,
  "Bobi Klintman": 0.9,
  "Bogdan Bogdanovi\u0107": 0.662,
  "Bol Bol": 0.577,
  "Bones Hyland": 0.544,
  "Bradley Beal": 0.551,
  "Branden Carlson": 0.667,
  "Brandin Podziemski": 0.457,
  "Brandon Boston": 0.656,
  "Brandon Clarke": 0.411,
  "Brandon Ingram": 0.519,
  "Brandon Miller": 0.474,
  "Brandon Williams": 0.414,
  "Brice Sensabaugh": 0.466,
  "Bronny James": 0.731,
  "Brook Lopez": 0.547,
  "Brooks Barnhizer": 0.885,
  "Bruce Brown": 0.556,
  "Bryce McGowens": 0.511,
  "Bub Carrington": 0.514,
  "Buddy Hield": 0.628,
  "CJ McCollum": 0.576,
  "Cade Cunningham": 0.471,
  "Caleb Houstan": 0.631,
  "Caleb Love": 0.541,
  "Caleb Martin": 0.731,
  "Cam Christie": 0.706,
  "Cam Spencer": 0.477,
  "Cam Thomas": 0.719,
  "Cam Whitmore": 0.548,
  "Cameron Johnson": 0.561,
  "Cameron Payne": 0.59,
  "Caris LeVert": 0.55,
  "Carter Bryant": 0.593,
  "Cason Wallace": 0.557,
  "Cedric Coward": 0.571,
  "Charles Bassey": 0.71,
  "Chaz Lanier": 0.833,
  "Chet Holmgren": 0.54,
  "Chris Boucher": 0.653,
  "Chris Livingston": 0.714,
  "Chris Paul": 0.591,
  "Chris Youngblood": 0.714,
  "Christian Braun": 0.555,
  "Christian Koloko": 0.627,
  "Clint Capela": 0.675,
  "Coby White": 0.431,
  "Cody Martin": 0.766,
  "Cody Williams": 0.676,
  "Colby Jones": 0.893,
  "Cole Anthony": 0.707,
  "Colin Castleton": 0.875,
  "Collin Gillespie": 0.701,
  "Collin Murray-Boyles": 0.786,
  "Collin Sexton": 0.583,
  "Cooper Flagg": 0.741,
  "Corey Kispert": 0.657,
  "Cory Joseph": 0.825,
  "Craig Porter Jr.": 0.703,
  "D'Angelo Russell": 0.716,
  "DaQuan Jeffries": 0.775,
  "DaRon Holmes II": 0.75,
  "Daeqwon Plowden": 0.87,
  "Dalano Banton": 0.79,
  "Dalen Terry": 0.627,
  "Dalton Knecht": 0.678,
  "Damian Lillard": 0.688,
  "Damion Lee": 0.8,
  "Daniel Gafford": 0.65,
  "Daniss Jenkins": 0.694,
  "Danny Wolf": 0.809,
  "Dant\u00e9 Exum": 1.0,
  "Dario \u0160ari\u0107": 0.818,
  "Darius Garland": 0.638,
  "David Roddy": 0.731,
  "Davion Mitchell": 0.643,
  "Day'Ron Sharpe": 0.667,
  "De'Aaron Fox": 0.641,
  "De'Andre Hunter": 0.616,
  "De'Anthony Melton": 0.615,
  "DeAndre Jordan": 0.707,
  "DeMar DeRozan": 0.493,
  "Dean Wade": 0.651,
  "Deandre Ayton": 0.604,
  "Dejounte Murray": 0.676,
  "Delon Wright": 0.9,
  "Deni Avdija": 0.659,
  "Dennis Schr\u00f6der": 0.623,
  "Dereck Lively II": 0.758,
  "Derik Queen": 0.754,
  "Derrick Jones Jr.": 0.667,
  "Derrick White": 0.616,
  "Desmond Bane": 0.615,
  "Devin Booker": 0.68,
  "Devin Carter": 0.678,
  "Devin Vassell": 0.667,
  "Dillon Brooks": 0.647,
  "Dillon Jones": 0.76,
  "Domantas Sabonis": 0.709,
  "Dominick Barlow": 0.644,
  "Donovan Clingan": 0.581,
  "Donovan Mitchell": 0.656,
  "Donte DiVincenzo": 0.654,
  "Dorian Finney-Smith": 0.659,
  "Doug McDermott": 0.786,
  "Drake Powell": 0.708,
  "Draymond Green": 0.633,
  "Drew Eubanks": 0.598,
  "Drew Peterson": 0.75,
  "Drew Timme": 0.857,
  "Dru Smith": 0.726,
  "Duncan Robinson": 0.632,
  "Duop Reath": 0.779,
  "Dwight Powell": 0.723,
  "Dylan Cardwell": 0.793,
  "Dylan Harper": 0.769,
  "Dyson Daniels": 0.623,
  "E.J. Liddell": 0.739,
  "Egor D\u00ebmin": 0.762,
  "Elfrid Payton": 0.786,
  "Elijah Harkless": 0.615,
  "Enrique Freeman": 0.923,
  "Eric Gordon": 0.8,
  "Ethan Thompson": 1.0,
  "Evan Mobley": 0.615,
  "Franz Wagner": 0.722,
  "Fred VanVleet": 0.84,
  "GG Jackson": 0.775,
  "Gabe Vincent": 0.559,
  "Garrett Temple": 0.816,
  "Garrison Mathews": 0.824,
  "Gary Harris": 0.675,
  "Gary Payton II": 0.664,
  "Gary Trent Jr.": 0.633,
  "Georges Niang": 0.725,
  "Giannis Antetokounmpo": 0.581,
  "Goga Bitadze": 0.653,
  "Gradey Dick": 0.605,
  "Grant Williams": 0.784,
  "Grayson Allen": 0.683,
  "Guerschon Yabusele": 0.707,
  "Gui Santos": 0.645,
  "Harrison Barnes": 0.669,
  "Haywood Highsmith": 0.739,
  "Herbert Jones": 0.571,
  "Hugo Gonz\u00e1lez": 0.705,
  "Hunter Tyson": 0.689,
  "Immanuel Quickley": 0.733,
  "Isaac Jones": 0.833,
  "Isaac Okoro": 0.581,
  "Isaiah Collier": 0.7,
  "Isaiah Crawford": 0.941,
  "Isaiah Hartenstein": 0.6,
  "Isaiah Jackson": 0.8,
  "Isaiah Joe": 0.725,
  "Isaiah Livers": 0.885,
  "Isaiah Stewart": 0.667,
  "Ivica Zubac": 0.593,
  "JD Davison": 0.935,
  "JT Thor": 0.7,
  "Ja Morant": 0.667,
  "Ja'Kobe Walter": 0.741,
  "Jabari Smith Jr.": 0.655,
  "Jabari Walker": 0.721,
  "Jacob Toppin": 0.75,
  "Jaden Hardy": 0.663,
  "Jaden Ivey": 0.614,
  "Jaden McDaniels": 0.608,
  "Jaden Springer": 0.828,
  "Jae'Sean Tate": 0.707,
  "Jahmai Mashack": 0.812,
  "Jaime Jaquez Jr.": 0.675,
  "Jake LaRavia": 0.629,
  "Jakob Poeltl": 0.644,
  "Jalen Brunson": 0.656,
  "Jalen Duren": 0.609,
  "Jalen Green": 0.67,
  "Jalen Johnson": 0.638,
  "Jalen Pickett": 0.765,
  "Jalen Smith": 0.645,
  "Jalen Suggs": 0.684,
  "Jalen Williams": 0.562,
  "Jalen Wilson": 0.627,
  "Jamal Cain": 0.842,
  "Jamal Murray": 0.581,
  "Jamal Shead": 0.645,
  "Jamaree Bouyea": 0.778,
  "James Harden": 0.63,
  "Jamir Watkins": 0.75,
  "Jamison Battle": 0.699,
  "Jarace Walker": 0.645,
  "Jared Butler": 0.8,
  "Jared McCain": 0.743,
  "Jaren Jackson Jr.": 0.705,
  "Jarred Vanderbilt": 0.624,
  "Jarrett Allen": 0.648,
  "Jase Richardson": 0.8,
  "Javon Small": 0.821,
  "Javonte Green": 0.597,
  "Jaxson Hayes": 0.645,
  "Jay Huff": 0.562,
  "Jaylen Brown": 0.575,
  "Jaylen Clark": 0.699,
  "Jaylen Wells": 0.652,
  "Jaylin Williams": 0.704,
  "Jaylon Tyson": 0.733,
  "Jayson Tatum": 0.703,
  "Jeff Dowtin Jr.": 0.71,
  "Jeff Green": 0.7,
  "Jerami Grant": 0.649,
  "Jeremiah Fears": 0.636,
  "Jeremiah Robinson-Earl": 0.705,
  "Jeremy Sochan": 0.694,
  "Jericho Sims": 0.723,
  "Jett Howard": 0.606,
  "Jevon Carter": 0.658,
  "Jimmy Butler III": 0.639,
  "Joan Beringer": 0.88,
  "Jock Landale": 0.63,
  "Joe Ingles": 0.875,
  "Joel Embiid": 0.667,
  "John Collins": 0.602,
  "John Konchar": 0.698,
  "Johnny Furphy": 0.73,
  "Johnny Juzang": 0.757,
  "Jonas Valan\u010di\u016bnas": 0.687,
  "Jonathan Isaac": 0.685,
  "Jonathan Kuminga": 0.638,
  "Jonathan Mogbo": 0.75,
  "Jordan Clarkson": 0.649,
  "Jordan Goodwin": 0.635,
  "Jordan Hawkins": 0.652,
  "Jordan McLaughlin": 0.867,
  "Jordan Miller": 0.667,
  "Jordan Poole": 0.663,
  "Jordan Walsh": 0.706,
  "Jose Alvarado": 0.688,
  "Josh Giddey": 0.743,
  "Josh Green": 0.655,
  "Josh Hart": 0.628,
  "Josh Minott": 0.707,
  "Josh Okogie": 0.686,
  "Jrue Holiday": 0.73,
  "Julian Champagnie": 0.694,
  "Julian Phillips": 0.69,
  "Julian Strawther": 0.645,
  "Julius Randle": 0.634,
  "Justin Champagnie": 0.704,
  "Justin Edwards": 0.75,
  "Jusuf Nurki\u0107": 0.695,
  "KJ Martin": 0.848,
  "KJ Simpson": 0.818,
  "Kai Jones": 0.767,
  "Kam Jones": 0.857,
  "Karl-Anthony Towns": 0.619,
  "Karlo Matkovi\u0107": 0.734,
  "Kasparas Jaku\u010dionis": 0.789,
  "Kawhi Leonard": 0.655,
  "Keaton Wallace": 0.671,
  "Keegan Murray": 0.607,
  "Kel'el Ware": 0.683,
  "Keldon Johnson": 0.613,
  "Kelly Olynyk": 0.784,
  "Kelly Oubre Jr.": 0.681,
  "Kenrich Williams": 0.67,
  "Kentavious Caldwell-Pope": 0.686,
  "Keon Ellis": 0.657,
  "Keon Johnson": 0.565,
  "Keshad Johnson": 0.788,
  "Kessler Edwards": 0.759,
  "Kevin Durant": 0.664,
  "Kevin Huerter": 0.659,
  "Kevin Love": 0.78,
  "Kevin McCullar Jr.": 0.75,
  "Kevin Porter Jr.": 0.728,
  "Kevon Looney": 0.671,
  "Keyonte George": 0.64,
  "Khaman Maluach": 0.774,
  "Khris Middleton": 0.655,
  "Killian Hayes": 1.0,
  "Klay Thompson": 0.669,
  "Kobe Brown": 0.735,
  "Kobe Bufkin": 0.923,
  "Kobe Sanders": 0.788,
  "Kon Knueppel": 0.8,
  "Kris Dunn": 0.614,
  "Kris Murray": 0.73,
  "Kristaps Porzi\u0146\u0123is": 0.7,
  "Kyle Anderson": 0.632,
  "Kyle Filipowski": 0.669,
  "Kyle Kuzma": 0.653,
  "Kyle Lowry": 0.842,
  "Kyrie Irving": 0.725,
  "Kyshawn George": 0.623,
  "LaMelo Ball": 0.66,
  "Lachlan Olbrich": 0.8,
  "Landry Shamet": 0.598,
  "Larry Nance Jr.": 0.756,
  "Lauri Markkanen": 0.658,
  "LeBron James": 0.704,
  "Leonard Miller": 0.721,
  "Liam McNeeley": 0.75,
  "Lindy Waters III": 0.778,
  "Lonzo Ball": 0.683,
  "Luguentz Dort": 0.629,
  "Luka Don\u010di\u0107": 0.612,
  "Luka Garza": 0.681,
  "Luke Kennard": 0.693,
  "Luke Kornet": 0.632,
  "Luke Travers": 0.571,
  "Malaki Branham": 0.726,
  "Malcolm Brogdon": 0.571,
  "Malevy Leons": 0.812,
  "Malik Beasley": 0.764,
  "Malik Monk": 0.684,
  "MarJon Beauchamp": 0.865,
  "Marcus Sasser": 0.696,
  "Marcus Smart": 0.655,
  "Mark Williams": 0.678,
  "Markelle Fultz": 0.812,
  "Marvin Bagley III": 0.662,
  "Mason Plumlee": 0.707,
  "Matas Buzelis": 0.6,
  "Matisse Thybulle": 0.833,
  "Max Christie": 0.626,
  "Max Strus": 0.702,
  "Maxi Kleber": 0.729,
  "Maxime Raynaud": 0.729,
  "Maxwell Lewis": 0.706,
  "Micah Peavy": 0.756,
  "Micah Potter": 0.681,
  "Michael Porter Jr.": 0.689,
  "Mikal Bridges": 0.581,
  "Mike Conley": 0.64,
  "Miles Bridges": 0.632,
  "Miles McBride": 0.67,
  "Mitchell Robinson": 0.719,
  "Mohamed Diawara": 0.691,
  "Mont\u00e9 Morris": 0.854,
  "Moritz Wagner": 0.759,
  "Moses Moody": 0.605,
  "Mouhamed Gueye": 0.635,
  "Moussa Cisse": 0.833,
  "Moussa Diabat\u00e9": 0.656,
  "Myles Turner": 0.585,
  "Myron Gardner": 0.867,
  "Nae'Qwan Tomlin": 0.564,
  "Naji Marshall": 0.646,
  "Nate Williams": 0.905,
  "Naz Reid": 0.627,
  "Neemias Queta": 0.612,
  "Nic Claxton": 0.664,
  "Nick Richards": 0.777,
  "Nick Smith Jr.": 0.64,
  "Nickeil Alexander-Walker": 0.644,
  "Nicolas Batum": 0.645,
  "Nikola Joki\u0107": 0.603,
  "Nikola Jovi\u0107": 0.667,
  "Nikola Vu\u010devi\u0107": 0.642,
  "Nique Clifford": 0.683,
  "Noah Clowney": 0.634,
  "Noah Penda": 0.682,
  "Nolan Traore": 0.762,
  "Norman Powell": 0.676,
  "OG Anunoby": 0.661,
  "Obi Toppin": 0.644,
  "Ochai Agbaji": 0.687,
  "Olivier-Maxence Prosper": 0.641,
  "Onyeka Okongwu": 0.619,
  "Oscar Tshiebwe": 0.692,
  "Oso Ighodaro": 0.683,
  "Ousmane Dieng": 0.731,
  "P.J. Washington": 0.627,
  "PJ Hall": 0.731,
  "Pac\u00f4me Dadiet": 0.848,
  "Paolo Banchero": 0.569,
  "Pascal Siakam": 0.667,
  "Pat Connaughton": 0.735,
  "Pat Spencer": 0.716,
  "Patrick Baldwin Jr.": 0.739,
  "Patrick Williams": 0.622,
  "Patty Mills": 0.684,
  "Paul George": 0.661,
  "Paul Reed": 0.745,
  "Payton Pritchard": 0.66,
  "Pelle Larsson": 0.682,
  "Pete Nance": 0.739,
  "Peyton Watson": 0.643,
  "Precious Achiuwa": 0.678,
  "Quentin Grimes": 0.701,
  "Quenton Jackson": 0.754,
  "Quinten Post": 0.636,
  "RJ Barrett": 0.62,
  "Rasheer Fleming": 0.825,
  "RayJ Dennis": 0.882,
  "Rayan Rupert": 0.676,
  "Reece Beekman": 0.8,
  "Reed Sheppard": 0.61,
  "Richaun Holmes": 0.667,
  "Ricky Council IV": 0.698,
  "Rob Dillingham": 0.694,
  "Robert Williams III": 0.766,
  "Ron Harper Jr.": 0.867,
  "Ronald Holland II": 0.636,
  "Royce O'Neale": 0.667,
  "Rudy Gobert": 0.612,
  "Rui Hachimura": 0.667,
  "Russell Westbrook": 0.636,
  "Ryan Dunn": 0.685,
  "Ryan Kalkbrenner": 0.585,
  "Ryan Nembhard": 0.756,
  "Ryan Rollins": 0.744,
  "Saddiq Bey": 0.661,
  "Sam Hauser": 0.59,
  "Sam Merrill": 0.691,
  "Sandro Mamukelashvili": 0.742,
  "Santi Aldama": 0.592,
  "Scoot Henderson": 0.716,
  "Scottie Barnes": 0.597,
  "Scotty Pippen Jr.": 0.671,
  "Seth Curry": 0.726,
  "Shaedon Sharpe": 0.7,
  "Shai Gilgeous-Alexander": 0.577,
  "Shake Milton": 0.723,
  "Sharife Cooper": 0.88,
  "Sidy Cissoko": 0.688,
  "Simone Fontecchio": 0.594,
  "Sion James": 0.606,
  "Spencer Dinwiddie": 0.754,
  "Spencer Jones": 0.803,
  "Stanley Umude": 1.0,
  "Stephen Curry": 0.697,
  "Stephon Castle": 0.619,
  "Steven Adams": 0.628,
  "Svi Mykhailiuk": 0.632,
  "T.J. McConnell": 0.637,
  "Taelon Peter": 0.818,
  "Taj Gibson": 0.912,
  "Talen Horton-Tucker": 0.833,
  "Tari Eason": 0.743,
  "Taurean Prince": 0.711,
  "Taylor Hendricks": 0.673,
  "Terance Mann": 0.689,
  "Terrence Shannon Jr.": 0.724,
  "Terry Rozier": 0.667,
  "Thanasis Antetokounmpo": 0.842,
  "Thomas Bryant": 0.719,
  "Tidjane Sala\u00fcn": 0.709,
  "Tim Hardaway Jr.": 0.622,
  "Tobias Harris": 0.62,
  "Tony Bradley": 0.775,
  "Torrey Craig": 0.75,
  "Tosan Evbuomwan": 0.783,
  "Toumani Camara": 0.621,
  "Trae Young": 0.691,
  "Trayce Jackson-Davis": 0.69,
  "Tre Johnson": 0.714,
  "Tre Jones": 0.632,
  "Tre Mann": 0.75,
  "Trendon Watford": 0.726,
  "Trevelin Queen": 0.8,
  "Trey Alexander": 0.833,
  "Trey Jemison III": 0.763,
  "Trey Lyles": 0.763,
  "Trey Murphy III": 0.626,
  "Tristan Thompson": 0.933,
  "Tristan Vukcevic": 0.662,
  "Tristan da Silva": 0.667,
  "Ty Jerome": 0.693,
  "TyTy Washington Jr.": 0.938,
  "Tyler Herro": 0.619,
  "Tyler Kolek": 0.733,
  "Tyler Smith": 0.8,
  "Tyrese Haliburton": 0.635,
  "Tyrese Martin": 0.663,
  "Tyrese Maxey": 0.604,
  "Tyrese Proctor": 0.833,
  "Tyson Etienne": 0.75,
  "Tyus Jones": 0.585,
  "VJ Edgecombe": 0.661,
  "Vasilije Micic": 0.806,
  "Victor Wembanyama": 0.646,
  "Vince Williams Jr.": 0.684,
  "V\u00edt Krej\u010d\u00ed": 0.712,
  "Walker Kessler": 0.736,
  "Walter Clayton Jr.": 0.589,
  "Wendell Carter Jr.": 0.685,
  "Wendell Moore Jr.": 0.677,
  "Will Richard": 0.667,
  "Will Riley": 0.707,
  "Xavier Tillman": 0.872,
  "Yang Hansen": 0.733,
  "Yanic Konan Niederh\u00e4user": 0.833,
  "Yuki Kawamura": 0.87,
  "Yves Missi": 0.611,
  "Zaccharie Risacher": 0.664,
  "Zach Collins": 0.75,
  "Zach Edey": 0.746,
  "Zach LaVine": 0.709,
  "Zeke Nnaji": 0.677,
  "Ziaire Williams": 0.667,
  "Zion Williamson": 0.684
}